[
  {
    "id": "7c2f6dd6-b0c5-481b-9423-27d1cb02af99",
    "name": "Test car",
    "repairs": [
      {
        "id": "a1a31fa0-d589-4296-b62c-1a0ff438a66d",
        "date": "2020-11-14T11:03:00.316304",
        "milage": 200,
        "price": 0.0,
        "reason": "Időszakos",
        "items": ["Motor olaj"],
        "description": "Rendszeres olajcsere",
        "warranty": true
      }
    ],
    "refuels": [
      {
        "id": "975503c6-9b8b-43f2-ac06-48157ba9c633",
        "date": "2020-11-14T11:03:00.315294",
        "refueled": 14.0,
        "paid": 5740.0,
        "lastMilage": 0,
        "milage": 200
      }
    ],
    "reminds": [
      {
        "id": "6f12e138-3014-4a48-909c-30b3e901cff5",
        "name": "Kötelező",
        "description": "Kötelező biztosítás évente",
        "items": ["biztosítás"],
        "date": "2020-11-14T11:03:00.315294",
        "afterDays": 365,
        "startMilage": null,
        "afterMilage": null,
        "completed": false
      }
    ],
    "eVignettes": [
      {
        "id": "dff66be0-54ae-426f-a864-8b8bfc05efe1",
        "start": "2020-11-14T11:03:00.314304",
        "duration": 2,
        "area": "Magyarország"
      }
    ],
    "tire": "Winter",
    "settings": { "image": "url", "cost": 1000000.0, "year": 2004 }
  }
]
